cuckoos/__init__.py
cuckoos/flock.py
cuckoos/nest.py
cuckoos/utils.py
cuckoos-0.1.2.dist-info/DESCRIPTION.rst
cuckoos-0.1.2.dist-info/METADATA
cuckoos-0.1.2.dist-info/RECORD
cuckoos-0.1.2.dist-info/WHEEL
cuckoos-0.1.2.dist-info/metadata.json
cuckoos-0.1.2.dist-info/top_level.txt
